setup.py
lp_api_kernel/__init__.py
lp_api_kernel/exceptions.py
lp_api_kernel.egg-info/PKG-INFO
lp_api_kernel.egg-info/SOURCES.txt
lp_api_kernel.egg-info/dependency_links.txt
lp_api_kernel.egg-info/requires.txt
lp_api_kernel.egg-info/top_level.txt
lp_api_kernel/cache/__init__.py
lp_api_kernel/cache/remote.py
lp_api_kernel/external/__init__.py
lp_api_kernel/internal/__init__.py