Metadata-Version: 1.0
Name: lp-api-kernel
Version: 1.1.0
Summary: Basic API's for the Linux Portal.
Home-page: https://github.com/InfrabelLinux/linuxportal-api-kernel
Author: Infrabel Linux Team
Author-email: linux@infrabel.be
License: Apache
Platform: UNKNOWN
